{
  "node-cli": {
    "node": "6.14.4",
    "npm_version": "6.7.0",
    "main": "lib/cli/etcher.js",
    "dependencies": {
      "linux": [
        "libudev-dev",
        "libusb-1.0-0-dev"
      ]
    }
  },
  "electron": {
    "npm_version": "6.7.0",
    "dependencies": {
      "linux": [
        "libudev-dev",
        "libusb-1.0-0-dev",
        "libyaml-dev",
        "libgtk-3-0",
        "libatk-bridge2.0-0",
        "libdbus-1-3",
        "libc6"
      ]
    },
    "builder": {
      "appId": "io.balena.etcher",
      "copyright": "Copyright 2016-2018 Balena Ltd",
      "productName": "balenaEtcher",
      "nodeGypRebuild": true,
      "files": [
        "!lib/gui/app",
        "lib/gui/app/index.html",
        "generated"
      ],
      "mac": {
        "category": "public.app-category.developer-tools"
      },
      "dmg": {
        "iconSize": 110,
        "contents": [
          {
            "x": 140,
            "y": 245
          },
          {
            "x": 415,
            "y": 245,
            "type": "link",
            "path": "/Applications"
          }
        ],
        "window": {
          "width": 544,
          "height": 407
        }
      },
      "linux": {
        "category": "Utility",
        "packageCategory": "utils",
        "synopsis": "balenaEtcher is a powerful OS image flasher built with web technologies to ensure flashing an SDCard or USB drive is a pleasant and safe experience. It protects you from accidentally writing to your hard-drives, ensures every byte of data was written correctly and much more."
      },
      "deb": {
        "priority": "optional",
        "depends": [
          "polkit-1-auth-agent | policykit-1-gnome | polkit-kde-1"
        ]
      }
    }
  }
}
